{
  "pools": [
    {
      "rolls": 1,
      "entries": [
        {
          "type": "minecraft:item",
          "name": "minecraft:structure_block",
          "functions": [
            {
              "function": "minecraft:set_nbt",
              "tag": "{display:{Name:'{\"text\":\"Air Rune\",\"color\":\"gold\"}',Lore:['[{\"text\":\"Levitate\",\"color\":\"gold\",\"bold\":true},{\"text\":\" - 2 \uE003\",\"color\":\"white\",\"italic\":true}]','{\"text\":\"Throws hit target into air. When hitting players, gives slowfall briefly.\",\"color\":\"dark_aqua\"}']},HideFlags:127,CustomModelData:204,cl.isRune:1b,cl.spellNumber:403}"
            }
          ]
        }
      ]
    }
  ]
}
