{
    "display": {
        "title": {
            "text": "Summon Iron Golem",
            "color": "green"
        },
        "description": {
            "text": "Learn Summon Iron Golem",
            "color": "white"
        },
        "icon": {
            "item": "minecraft:warped_fungus_on_a_stick",
            "nbt": "{CustomModelData:60504}"
        },
        "frame": "task",
        "show_toast": true,
        "announce_to_chat": false,
        "hidden": true
    },
    "criteria": {
        "Iron Golem": {
            "trigger": "minecraft:impossible"
        }
    },
    "parent": "classes:mage/learnspell/earth/poison"
}
